owasp_checker_v2/__init__.py
owasp_checker_v2/cli.py
owasp_checker_v2/dependency_checker.py
owasp_checker_v2/owasp_checker.py
owasp_checker_v2/owasp_scraper.py
owasp_checker_v2/owasp_top_ten_scanner.py
owasp_checker_v2/risk_prioritizer.py
owasp_checker_v2/threat_intelligence_checker.py
owasp_checker_v2-1.0.0.dist-info/LICENSE
owasp_checker_v2-1.0.0.dist-info/METADATA
owasp_checker_v2-1.0.0.dist-info/WHEEL
owasp_checker_v2-1.0.0.dist-info/entry_points.txt
owasp_checker_v2-1.0.0.dist-info/top_level.txt
owasp_checker_v2-1.0.0.dist-info/RECORD
