Metadata-Version: 2.1
Name: owasp-checker-v2
Version: 1.0.0
Summary: Enhanced OWASP Top Ten Compliance Checker Library
Home-page: https://github.com/abidi-bassem/owasp-checker-v2
Author: ABidi Bassem
Author-email: abidi.bassem@me.com
Project-URL: Documentation, https://github.com/abidi-bassem/owasp-checker-v2/docs
Project-URL: Source, https://github.com/abidi-bassem/owasp-checker-v2
Project-URL: Tracker, https://github.com/abidi-bassem/owasp-checker-v2/issues
Keywords: security,owasp,vulnerability,scanner,dependency-checker,threat-intelligence
Classifier: Development Status :: 5 - Production/Stable
Classifier: Intended Audience :: Developers
Classifier: Intended Audience :: Information Technology
Classifier: Intended Audience :: System Administrators
Classifier: License :: OSI Approved :: MIT License
Classifier: Operating System :: OS Independent
Classifier: Programming Language :: Python :: 3
Classifier: Programming Language :: Python :: 3.8
Classifier: Programming Language :: Python :: 3.9
Classifier: Programming Language :: Python :: 3.10
Classifier: Programming Language :: Python :: 3.11
Classifier: Topic :: Security
Classifier: Topic :: Software Development :: Libraries :: Python Modules
Classifier: Topic :: Software Development :: Testing
Requires-Python: >=3.8
License-File: LICENSE
Requires-Dist: requests >=2.25.0
Requires-Dist: beautifulsoup4 >=4.9.3
Requires-Dist: python-owasp-zap-v2.4 >=0.0.20
Requires-Dist: packaging >=21.0
Requires-Dist: nvdlib >=0.7.0
Requires-Dist: vt-py >=0.7.0
Requires-Dist: tqdm >=4.62.0
Requires-Dist: python-dateutil >=2.8.2
Requires-Dist: urllib3 >=1.26.0
Requires-Dist: certifi >=2021.10.8
Requires-Dist: click >=8.0.0
Requires-Dist: colorama >=0.4.4
Requires-Dist: rich >=10.0.0
Requires-Dist: typing-extensions >=4.0.0 ; python_version < "3.9"
Provides-Extra: dev
Requires-Dist: pytest >=6.0.0 ; extra == 'dev'
Requires-Dist: pytest-cov >=2.0.0 ; extra == 'dev'
Requires-Dist: black >=21.0.0 ; extra == 'dev'
Requires-Dist: isort >=5.0.0 ; extra == 'dev'
Requires-Dist: mypy >=0.900 ; extra == 'dev'
Requires-Dist: flake8 >=3.9.0 ; extra == 'dev'
